npsolve/__init__.py
npsolve/core.py
npsolve/soft_functions.py
npsolve/solvers.py
npsolve/legacy/__init__.py
npsolve/legacy/legacy_cache.py
npsolve/legacy/legacy_core.py
npsolve/legacy/legacy_solver.py
npsolve/legacy/legacy_utils.py
npsolve-1.0.3.dist-info/METADATA
npsolve-1.0.3.dist-info/WHEEL
npsolve-1.0.3.dist-info/licenses/LICENSE
npsolve-1.0.3.dist-info/RECORD
