Metadata-Version: 2.4
Name: npsolve
Version: 1.0.3
Summary: Easier object-oriented calculations for numerical solvers.
Project-URL: Homepage, https://github.com/pythoro/npsolve.git
Project-URL: Repository, https://github.com/pythoro/npsolve.git
Project-URL: Documentation, https://npsolve.readthedocs.io/en/latest/
Author-email: Reuben Rusk <pythoro@mindquip.com>
Maintainer-email: Reuben Rusk <pythoro@mindquip.com>
License-Expression: MIT
License-File: LICENSE
Keywords: INTEGRATION,NUMERICAL SOLVER,NUMPY,ODE,SCIPY
Classifier: Operating System :: OS Independent
Classifier: Programming Language :: Python :: 3
Requires-Python: ~=3.9
Requires-Dist: numpy>=1.16.4
